veritorch/__init__.py
veritorch/veritorch.py
veritorch-0.1.1.dist-info/METADATA
veritorch-0.1.1.dist-info/WHEEL
veritorch-0.1.1.dist-info/top_level.txt
veritorch-0.1.1.dist-info/RECORD
