Metadata-Version: 2.1
Name: veritorch
Version: 0.1.1
Summary: autodifferentiation package, supporting both forward mode and backward mode right now
Home-page: https://github.com/veritorch/cs207-FinalProject
Author: Yixing Guan, Yinan Shen, Shuying Ni, Banruo(Rock) Zhou
Author-email: yixingguan@fas.harvard.edu, yinanshen@g.harvard.edu, shuying_ni@g.harvard.edu, bzhou@g.harvard.edu
License: UNKNOWN
Platform: UNKNOWN
Classifier: Programming Language :: Python :: 3
Classifier: License :: OSI Approved :: MIT License
Classifier: Operating System :: OS Independent
Requires-Python: >=3.6
Requires-Dist: numpy (==1.17.3)
Requires-Dist: pytest (==5.2.2)
